[
  {
    "jira_key": "SCRUM-2",
    "summary": "Task 2",
    "description": "",
    "reporter": "Rusha Dutta",
    "stakeholders": "",
    "evidence": "",
    "module": "",
    "session_id": "f0d3d492-67e9-427f-ae8e-347ab70c5548",
    "facilitator_id": "cbc@cbc.com",
    "timestamp": "2025-11-05T17:33:57Z",
    "value_agreement": "delivers customer value and boosts brand perception",
    "dissent": "high amount of refactoring needed",
    "dependencies": "infrastructure expansion",
    "biases": "high interest by upper management",
    "synthesis_summary": "good item to pursue as it will be beneficial to the org in immediate future"
  },
  {
    "jira_key": "SCRUM-5",
    "summary": "Security Enhancement",
    "description": "",
    "reporter": "Rusha Dutta",
    "stakeholders": "",
    "evidence": "",
    "module": "",
    "session_id": "f0d3d492-67e9-427f-ae8e-347ab70c5548",
    "facilitator_id": "cbc@cbc.com",
    "timestamp": "2025-11-05T17:35:12Z",
    "value_agreement": "boosts performance",
    "dissent": "not urgent",
    "dependencies": "none",
    "biases": "none",
    "synthesis_summary": "easy win but not urgent from business or customer perspective"
  }
]